{
	"enhancedScene": {
		"class" : "GuiDiv",
		"params" : {
			"parent" : "#root",
			"style" : "enhancedScene",
			"enhancedScene" : true
		}
	},
	"mainScene": {
		"class" : "GuiDiv",
		"params" : {
			"parent" : "enhancedScene",
			"style" : "mainScene",
			"innerScene" : true
		}
	},
	"backToMenu" : {
		"class" : "GuiButton",
		"params" : {
			"parent" : "enhancedScene",
			"normal" : {
				"image" : "buttons/friends.png",
				"source": "ButtonFriends.svg"
			},		
			"hover" : {
				"image" : "buttons/friendsOn.png",
				"source": "ButtonFriendsOn.svg",
				"scale" : 120
			},
			"active" : {
				"image" : "buttons/friendsOn.png",
				"source": "ButtonFriendsOn.svg"
			},
			"style" : "dialogButton", 
			"width" : 70, 
			"height" : 60,		
			"x" : 400,
			"y" : 30
		}
	}
}